pyfin_trading/__init__.py
pyfin_trading/indicators.py
pyfin_trading/stats.py
pyfin_trading/stock_data.py
pyfin_trading-1.0.0.dist-info/LICENSE
pyfin_trading-1.0.0.dist-info/METADATA
pyfin_trading-1.0.0.dist-info/WHEEL
pyfin_trading-1.0.0.dist-info/top_level.txt
pyfin_trading-1.0.0.dist-info/RECORD
