Metadata-Version: 2.1
Name: pyfin-trading
Version: 1.0.0
Summary: Making Finance easy in Python!
Author: Poonam Deshmukh
Author-email: poonamdeshmukh616@gmail.com
Keywords: python,finance,algorithmic trading,technical indicators
Classifier: Development Status :: 1 - Planning
Classifier: Intended Audience :: Developers
Classifier: Programming Language :: Python :: 3
Classifier: Operating System :: Unix
Classifier: Operating System :: MacOS :: MacOS X
Classifier: Operating System :: Microsoft :: Windows
License-File: LICENSE
